tuler/__init__.py
tuler/help.py
tuler-0.1.0.dist-info/METADATA
tuler-0.1.0.dist-info/WHEEL
tuler-0.1.0.dist-info/top_level.txt
tuler-0.1.0.dist-info/RECORD
