Metadata-Version: 2.1
Name: tuler
Version: 0.1.0
Summary: CLI + config application
Requires-Python: >=3.13
Requires-Dist: colorama>=0.4.6
